xumes/__init__.py
xumes/__main__.py
xumes/assertions/__init__.py
xumes/assertions/assertion.py
xumes/assertions/assertion_bucket.py
xumes/assertions/assertion_factory.py
xumes/assertions/assertion_result.py
xumes/communication/__init__.py
xumes/communication/i_com_game_engine.py
xumes/communication/i_com_game_instance.py
xumes/communication/implementations/__init__.py
xumes/communication/implementations/rest_impl/__init__.py
xumes/communication/implementations/rest_impl/com_game_engine_rest.py
xumes/communication/implementations/socket_impl/__init__.py
xumes/communication/implementations/socket_impl/com_game_instance_socket.py
xumes/core/colors.py
xumes/core/model_helper.py
xumes/core/modes.py
xumes/core/parameters_registry.py
xumes/core/registry.py
xumes/core/singleton.py
xumes/core/step.py
xumes/core/utils.py
xumes/core/xumes_cli.py
xumes/core/errors/running_ends_error.py
xumes/entity/__init__.py
xumes/entity/entity_manager.py
xumes/entity/game_element_state.py
xumes/entity/i_game_element_state_converter.py
xumes/entity/i_state_entity.py
xumes/entity/implementations/__init__.py
xumes/entity/implementations/json_impl/__init__.py
xumes/entity/implementations/json_impl/json_game_element_state_converter.py
xumes/modules/__init__.py
xumes/modules/godot/__init__.py
xumes/modules/godot/input/__init__.py
xumes/modules/godot/input/action.py
xumes/modules/godot/input/event.py
xumes/modules/godot/input/joy_button.py
xumes/modules/godot/input/joy_motion.py
xumes/modules/godot/input/mouse_motion.py
xumes/modules/godot/step/__init__.py
xumes/modules/godot/step/godot_action.py
xumes/modules/godot/step/godot_joy_action.py
xumes/modules/godot/step/godot_joy_direction.py
xumes/modules/human/__init__.py
xumes/modules/human/human_playing_test_manager.py
xumes/modules/imitation_learning/__init__.py
xumes/modules/imitation_learning/airl.py
xumes/modules/imitation_learning/bc.py
xumes/modules/imitation_learning/collector_test_manager.py
xumes/modules/imitation_learning/gail.py
xumes-0.3.0.dist-info/LICENSE
xumes-0.3.0.dist-info/METADATA
xumes-0.3.0.dist-info/WHEEL
xumes-0.3.0.dist-info/entry_points.txt
xumes-0.3.0.dist-info/top_level.txt
xumes-0.3.0.dist-info/RECORD
