Metadata-Version: 2.1
Name: xumes
Version: 0.3.0
Summary: A game testing tool.
Author-email: Vincent Mastain <vincentmastain@gmail.com>
Project-URL: homepage, https://github.com/mastainvin/Xumes
Project-URL: bug-tracker, https://github.com/mastainvin/Xumes/issues
Classifier: Programming Language :: Python :: 3
Classifier: License :: OSI Approved :: MIT License
Classifier: Operating System :: OS Independent
Requires-Python: >=3.8
License-File: LICENSE
Requires-Dist: gymnasium>=0.28.1
Requires-Dist: numpy>=1.23.5
Requires-Dist: sb3-contrib>=2.0.0a1
Requires-Dist: stable-baselines3>=2.0.0a1
Requires-Dist: requests>=2.30.0
Requires-Dist: statsmodels>=0.14.0
Requires-Dist: gherkin-official>=24.1.0
Requires-Dist: multiprocess>=0.70.14
Requires-Dist: furo
Requires-Dist: click>=8.1.7
Requires-Dist: tabulate>=0.9.0
Requires-Dist: tensorboard>=2.14.0
Requires-Dist: torchvision>=0.18.1
Requires-Dist: pygame
Requires-Dist: imitation
Requires-Dist: sphinx-copybutton
